dcicutils/__init__.py
dcicutils/base.py
dcicutils/beanstalk_utils.py
dcicutils/bundle_utils.py
dcicutils/captured_output.py
dcicutils/cloudformation_utils.py
dcicutils/codebuild_utils.py
dcicutils/command_utils.py
dcicutils/common.py
dcicutils/contribution_scripts.py
dcicutils/contribution_utils.py
dcicutils/creds_utils.py
dcicutils/data_readers.py
dcicutils/data_utils.py
dcicutils/datetime_utils.py
dcicutils/deployment_utils.py
dcicutils/diff_utils.py
dcicutils/docker_utils.py
dcicutils/ecr_scripts.py
dcicutils/ecr_utils.py
dcicutils/ecs_utils.py
dcicutils/env_base.py
dcicutils/env_manager.py
dcicutils/env_scripts.py
dcicutils/env_utils.py
dcicutils/env_utils_legacy.py
dcicutils/es_utils.py
dcicutils/exceptions.py
dcicutils/ff_mocks.py
dcicutils/ff_utils.py
dcicutils/file_utils.py
dcicutils/function_cache_decorator.py
dcicutils/glacier_utils.py
dcicutils/hack_for_elasticsearch_numpy_usage.py
dcicutils/http_utils.py
dcicutils/jh_utils.py
dcicutils/kibana/dashboards.json
dcicutils/kibana/readme.md
dcicutils/lang_utils.py
dcicutils/license_policies/c4-infrastructure.jsonc
dcicutils/license_policies/c4-python-infrastructure.jsonc
dcicutils/license_policies/park-lab-common-server.jsonc
dcicutils/license_policies/park-lab-common.jsonc
dcicutils/license_policies/park-lab-gpl-pipeline.jsonc
dcicutils/license_policies/park-lab-pipeline.jsonc
dcicutils/license_utils.py
dcicutils/log_utils.py
dcicutils/misc_utils.py
dcicutils/obfuscation_utils.py
dcicutils/opensearch_utils.py
dcicutils/portal_object_utils.py
dcicutils/portal_utils.py
dcicutils/progress_bar.py
dcicutils/project_utils.py
dcicutils/qa_checkers.py
dcicutils/qa_utils.py
dcicutils/redis_tools.py
dcicutils/redis_utils.py
dcicutils/s3_utils.py
dcicutils/schema_utils.py
dcicutils/scripts/publish_to_pypi.py
dcicutils/scripts/run_license_checker.py
dcicutils/scripts/update_portal_object.py
dcicutils/scripts/view_portal_object.py
dcicutils/secrets_utils.py
dcicutils/sheet_utils.py
dcicutils/snapshot_utils.py
dcicutils-8.18.3.dist-info/LICENSE.txt
dcicutils-8.18.3.dist-info/METADATA
dcicutils-8.18.3.dist-info/WHEEL
dcicutils-8.18.3.dist-info/entry_points.txt
dcicutils-8.18.3.dist-info/RECORD
