Metadata-Version: 2.1
Name: dcicutils
Version: 8.18.3
Summary: Utility package for interacting with the 4DN Data Portal and other 4DN resources
Home-page: https://github.com/4dn-dcic/utils
License: MIT
Author: 4DN-DCIC Team
Author-email: support@4dnucleome.org
Requires-Python: >=3.8.1,<3.13
Classifier: Development Status :: 4 - Beta
Classifier: Intended Audience :: Developers
Classifier: Intended Audience :: Science/Research
Classifier: License :: OSI Approved :: MIT License
Classifier: Programming Language :: Python :: 3
Classifier: Programming Language :: Python :: 3.9
Classifier: Programming Language :: Python :: 3.10
Classifier: Programming Language :: Python :: 3.11
Classifier: Programming Language :: Python :: 3
Classifier: Programming Language :: Python :: 3.10
Classifier: Programming Language :: Python :: 3.11
Classifier: Programming Language :: Python :: 3.12
Classifier: Programming Language :: Python :: 3.8
Classifier: Programming Language :: Python :: 3.9
Classifier: Topic :: Database :: Database Engines/Servers
Requires-Dist: PyJWT (>=2.6.0,<3.0.0)
Requires-Dist: PyYAML (>=6.0.1,<7.0.0)
Requires-Dist: appdirs (>=1.4.4,<2.0.0)
Requires-Dist: aws-requests-auth (>=0.4.2,<1)
Requires-Dist: boto3 (>=1.34.147,<2.0.0)
Requires-Dist: botocore (>=1.34.147,<2.0.0)
Requires-Dist: chardet (>=5.2.0,<6.0.0)
Requires-Dist: cryptography (>=43.0.1,<44.0.0)
Requires-Dist: docker (>=7.1.0,<8.0.0)
Requires-Dist: elasticsearch (==7.13.4)
Requires-Dist: gitpython (>=3.1.2,<4.0.0)
Requires-Dist: jsonc-parser (>=1.1.5,<2.0.0)
Requires-Dist: jsonschema (>=4.22.0,<5.0.0)
Requires-Dist: openpyxl (>=3.1.2,<4.0.0)
Requires-Dist: opensearch-py (>=2.0.1,<3.0.0)
Requires-Dist: pyopenssl (>=24.2.1,<25.0.0)
Requires-Dist: pyperclip (>=1.8.2,<2.0.0)
Requires-Dist: pyramid (==1.10.8)
Requires-Dist: pytz (>=2020.4)
Requires-Dist: redis (>=4.5.1,<5.0.0)
Requires-Dist: requests (>=2.27.1,<3.0.0)
Requires-Dist: rfc3986 (>=1.4.0,<2.0.0)
Requires-Dist: shortuuid (>=1.0.13,<2.0.0)
Requires-Dist: structlog (>=19.2.0,<20.0.0)
Requires-Dist: toml (>=0.10.1,<1)
Requires-Dist: tqdm (>=4.66.2,<5.0.0)
Requires-Dist: typing-extensions (>=3.8)
Requires-Dist: urllib3 (>=1.26.19,<2.0.0)
Requires-Dist: webtest (>=2.0.34,<3.0.0)
Project-URL: Repository, https://github.com/4dn-dcic/utils
